spasm/__init__.py
spasm/__main__.py
spasm/client.py
spasm/config.py
spasm-0.1.3.dist-info/entry_points.txt
spasm-0.1.3.dist-info/WHEEL
spasm-0.1.3.dist-info/METADATA
spasm-0.1.3.dist-info/RECORD
