Metadata-Version: 2.1
Name: spasm
Version: 0.1.3
Summary: A simple twitch.tv chat viewer.
Author: Jeremiah Boby
Author-email: mail@jeremiahboby.me
Requires-Python: >=3.9,<4.0
Classifier: Programming Language :: Python :: 3
Classifier: Programming Language :: Python :: 3.9
Requires-Dist: colorama (>=0.4.4,<0.5.0)
Requires-Dist: docopt (>=0.6.2,<0.7.0)
Requires-Dist: pydle (>=0.9.4,<0.10.0)
